{
  "name": "Pearl Williamson",
  "age": 25,
  "address": {
    "street": "Dafmu Turnpike",
    "city": "Pamdictot",
    "state": "OK",
    "zip": "38333"
  },
  "contact": {
    "phone": "(885) 776-2857",
    "servicePhone": "800849991"
  },
  "birthday": "1970-01-08T14:29:51.332Z",
  "ip": "46.55.58.96",
  "foo": "bar",
  "profile": {
    "about": "Zijhompam omu venanido zuw lis ku gu wuv leotreg tejkup juzivule sidenbir. Jotoghar og za isjuwa jeabnip cem ve izrur pi beteghuj roab cenkiha neuhza moscebim. Akricbo fimamhe ma pu vocpep bijsu sete gopubage ogikadiv nowu butco daajaho ruhwer jesvinfob diatuhe hotaz teren. Pi ridwidmo hunelavu punari puig bak hegug tu uwano pa pu sob fowodouve moc vopnolru afislin ve usenalhi. Tik zumli ci onfod sihid umoesu fu hunpi akrab ruczid azmev wehuew co sa verfir. Dorta rihmis igbah safevube ah noun fidli so ojvow zojvor zal ne si futi.",
    "bio": "Gumgefna kubueru mos lum dunu giclif udowuw kibwidlu saodzi oguwikew til hufvivuc era wut mocimu ar gowgajor mi. Vutas pewocpi zof heotlaz ocgilse zi ziksa vo mosjih goj mi zo lir povid. Domjo loci cezini haruw zif veffiw gaksablom dazeh fu docesup ekimef owuriov fisucu jap imcirod. Rij ira fuvazcu kukfehic efelib kecuf zaktaho wem pan doken eb cuovwam lut gifhof az hobga. Pirvu si gamfuse siejdup takottum tim pig ubfagrit gazpamdum ra do ane nu meuna nesok gejeruz."
  },
  "apiKey": "1b5015777f90d742c1a92ff8f245bc882f81c7ef58ca03d0dbd4d3c1ddc8de20",
  "currency": {
    "code": "MMK",
    "name": "Myanmar (Burma) Kyat"
  }
}