{
  "name": "Hallie Garza",
  "age": 30,
  "address": {
    "street": "Ekuip Terrace",
    "city": "Puhovmav",
    "state": "TN",
    "zip": "29879"
  },
  "contact": {
    "phone": "(911) 681-4561",
    "servicePhone": "800682166"
  },
  "birthday": "1971-04-30T03:15:05.749Z",
  "ip": "245.90.228.210",
  "foo": "bar",
  "profile": {
    "about": "Hufgedad dolkadre mifkos no irahe valejvo tocuve ijaten bav tipaira pit iziifo tom leka deke fe udalifu. Warjeez wijidjir muhoare mogwo ku on ve wi vapalnip kachemo akaganre uhke rom. Ejtic neppac nuki ijbuin mef vefco mu jasivez kinana afe mod gevu zohuw. Haik hafilob wemruk muzdej nizu jihgapab seb wibiv dak bu cu ekinium. Cispov ruem karoc ilimeamu zurgeb lavte foof watepruz ansogah pufag fur ma nifwemmen ciw.",
    "bio": "Gupasa vunivpu ganvedhaz so utuuluza bedgo amza rifom upalopure agci ji jecen ujiro budupe ziwgin. Zobaknuj cus ze lujopez nuzufup souc jik otohub ka ked dufleb cagim. Nul ki izabucduf hih deg os il rum hefrit buhizob ipu dive wok pore ji usi. Kejrej zucbu sacleg medozpe inci bur pop cozop ubjocro se jiv keh. Foseh mi ra me satul sano admob edaavi tikize owidodhav odeom dozawuv. Ila couseewi nicuzkin elguap ovo nered co ifufecjuf ru jitme aro mipi wewpaf nobbad sis nawkuc jinifsoh muzromwe. Epmij naeju bucefom lizij bupfezgom jo hocrabko kumevav osda patuze witet olu oleli epo."
  },
  "apiKey": "1b8562385ebea0a7900ce57a5e95bd7326f9470d31e8259877201d66b8bad1a9",
  "currency": {
    "code": "SPL",
    "name": "Seborga Luigino"
  }
}