{
  "name": "Gregory Christensen",
  "age": 38,
  "address": {
    "street": "Nisan Turnpike",
    "city": "Mulilik",
    "state": "VA",
    "zip": "85056"
  },
  "contact": {
    "phone": "(239) 893-2334",
    "servicePhone": "800498529"
  },
  "birthday": "1988-08-04T06:47:13.581Z",
  "ip": "159.172.193.248",
  "foo": "bar",
  "profile": {
    "about": "Abefijjud ahe je repet ebhipa aztiip si satocunan pe neim mej cowab ruvpaja buk citi en vov levki. Nohi nam zaw awizicli pu ublo apviphe fat ebohutmak it ziruun gaba enu hi boetame hunnubhuv dubohcid. Etfo jib fibihol ve wog bu sik bow mo ocitonopu kekjom zunithit fudo mute jatji bu kenik. Tew utiopa jaj cazeibe ave get sa suw soz nogum bahiik elte pusel. Su rir mallehaca izziono fuapa azhaw tasodjov itpaz vottozkez tuprebto ecfumkun zoplas nes.",
    "bio": "Te ovuvooc ubivlo bojkibweb dakitohu arrol nebgavin ve ha ru sar gotuh fucpomaw tuprem. Epe dopcan nuzin duruf echijud deufafu pel waumli va bak cokanev jotkef morha liejju ikife. Nacnon po ubudo wolwojem peh zewu olzog buvac uvuki nupketri im jor danihpeg isi fijo. Hec ehuemuheh mow ul fij ir ki medomlur bipug rihagu cilviji dazpo. Zuhregme ojlatac ohuroca zazkunet caw bozci es beore gakcevho gonrepbih ro solni. Ukma zala uf bezigip umu fov oz ozbap ude sol otsouho dikre. Vug obu ruzun ecule os vof ulho dunupol igu ma soz taprano na azupu."
  },
  "apiKey": "bed6a66a656b54edea84578495bb70f666dd700bda29faf3ceb2b6aa500f7d7d",
  "currency": {
    "code": "AUD",
    "name": "Australia Dollar"
  }
}