{
  "name": "Fred Riley",
  "age": 37,
  "address": {
    "street": "Zaje Street",
    "city": "Wedbevu",
    "state": "HI",
    "zip": "75141"
  },
  "contact": {
    "phone": "(803) 625-8415",
    "servicePhone": "800634613"
  },
  "birthday": "1992-06-04T10:06:34.655Z",
  "ip": "106.226.31.205",
  "foo": "bar",
  "profile": {
    "about": "Duthas emetaug apiutuko ircihaj uhivid tic owrarjiw possuma hemi fopulno ur onvi. Pu ru buloh durudik ezu zuhome tesnatpi izioda nuuma hajmeom lec on wi ivicav bez ko zenmezrod. Tikuvo jedez tuszem dab izfow zar eh fadarpil otredab tacjuebe hoaciuka edlizdu fe. Ciohjo duzu paspo taljate fitte hiev zaudkep wogegomiv datuzhog cimucis lifecis tobalcu kotbopge ica mu. Pagitgo esaara unoake damze of hokme fekre bo niwzuzso osu bajemufi wi ned. Jiicele moznal guluga lir sa ahovikje so rodo hepiv eti dar buji re. Pe pi runucsac ref unu ru ragevobe fo no nuf fihmug aherufibi orar icvajace nufofla cotmo.",
    "bio": "Ma rar pafojfi moer sisolic nezisvu dicfi zaig ute ziefi me luwo we padrat kesse. Ilfi cufnac avezofil pupbo gozuza we eknik wodi cih harvom ije lo haisi usitawat sizhahzu juic. Eweahzig moponod ikajepbem tezokpa venoruda mohame gemutto mamcemdem kibezug noz derko zoli duwpuzusa doeri oczonir ogo opdawfa."
  },
  "apiKey": "b4edd791ed1930ed868ba3acfc0bc67479a2ffdd67c2f5a0c6fbbb0c7c8faa93",
  "currency": {
    "code": "KRW",
    "name": "Korea (South) Won"
  }
}