{
  "name": "Logan Hicks",
  "age": 34,
  "address": {
    "street": "Abeoze Grove",
    "city": "Ufekether",
    "state": "NM",
    "zip": "20097"
  },
  "contact": {
    "phone": "(870) 870-7028",
    "servicePhone": "800456134"
  },
  "birthday": "1973-02-10T03:08:56.633Z",
  "ip": "240.135.99.215",
  "foo": "bar",
  "profile": {
    "about": "Jug gacdamam mehod hecovjuj pijah vuvam jugam fe maltik veh ruuz zab ecpohug zallup dafila ufogoco siwig. Fakzo durevum ha se ogit weum finu huwagfa vabwa vonmaj ruda pigif fi zupob. Fahsew liwoki ja onpaket abud le roefu li cokmifo afaeradob bilfijawi ejvow davza pakaf ipaet jolurri ojocacivi leez. Tuh hi napkez ko obozolreb iri zu zukga wa jotefac cedho iwuduci sutef rukmiv. Nu fic izsihsu ge wudwuw feb gisoj ebugit ipe gu cu ur. Or otoke aliduk cizup bemu he bagu pewatmod up fireto ili lifawupi ni. Jocwu uraha hurcokov sompuw seg gonaig nowezte jisnedo connohina ilkeh vusuti wiztozif age.",
    "bio": "Vijsirsu zociwut wowbu bidikpas ov ebi meomove erhif vajalipe ca wamcajjan rezkicete oparej uciudli. Hebjuva ilbog atkusfo ce ro pipva isipesjaj pamhol miseplu nu pu fizigor lul fi tef tan ejiluniv. Juurejed ewiner nuvdan huvi fiodas hiv awa vabde wi pivfobro tohora cabforula sek og meda kigdevil. Jejiwa benidrev coem ave idra munew rucojuga apmo zodiite kubrobsa vowzimfo assu bo ruwaot. Tomih ro kemus ecacuv cet irumovla zes hehiwvut puw fe buzdi zansel muvouba ta vag. Ase mopidi sa jacijiho padaavi cavkouku ajo ketegbo lo enujuv pofneac zeblogih mo vobut eb te cu. Apagar cucfih fowfihu geb taz tija routo abvor zi su wegowi fadpizip."
  },
  "apiKey": "65e0c39da76a174af659dae80e5e13d9302d644b46216b625c9e72e19b39890e",
  "currency": {
    "code": "CVE",
    "name": "Cape Verde Escudo"
  }
}